files_db.py
files_db2-0.2.dist-info/METADATA
files_db2-0.2.dist-info/WHEEL
files_db2-0.2.dist-info/RECORD
