Metadata-Version: 2.4
Name: files-db2
Version: 0.2
Summary: Create a database of all the items of a directory
Author-email: RadoTheProgrammer <rrrado15@gmail.com>
License-Expression: MIT
Classifier: Operating System :: OS Independent
Classifier: Programming Language :: Python :: 3
Requires-Python: >=3.13
Requires-Dist: pandas>=2.2.3
Requires-Dist: tqdm>=4.67.1
